loicmouquet_picsou/__init__.py
loicmouquet_picsou/picsou.py
loicmouquet_picsou-0.1.0.dist-info/METADATA
loicmouquet_picsou-0.1.0.dist-info/WHEEL
loicmouquet_picsou-0.1.0.dist-info/RECORD
